checker/__init__.py
checker/check.py
checker/circuit.py
checker/synthesizer.py
checker/verilog.py
verilogChecker-1.0.4.dist-info/METADATA
verilogChecker-1.0.4.dist-info/WHEEL
verilogChecker-1.0.4.dist-info/entry_points.txt
verilogChecker-1.0.4.dist-info/top_level.txt
verilogChecker-1.0.4.dist-info/RECORD
