Metadata-Version: 2.1
Name: verilogChecker
Version: 1.0.4
Summary: A tool for synthesizing and evaluating Verilog circuits.
Home-page: https://github.com/MortezaRezaalipour/VerilogChecker
Author: Morteza Rezaalipour
Author-email: morteza.rezaalipour@usi.ch
Classifier: Programming Language :: Python :: 3
Classifier: License :: OSI Approved :: MIT License
Classifier: Operating System :: OS Independent
Requires-Python: >=3.6
Requires-Dist: colorama
